gapless_crypto_data/__init__.py
gapless_crypto_data/__probe__.py
gapless_crypto_data/api.py
gapless_crypto_data/cli.py
gapless_crypto_data/collectors/__init__.py
gapless_crypto_data/collectors/binance_public_data_collector.py
gapless_crypto_data/collectors/concurrent_collection_orchestrator.py
gapless_crypto_data/collectors/httpx_downloader.py
gapless_crypto_data/collectors/hybrid_url_generator.py
gapless_crypto_data/gap_filling/__init__.py
gapless_crypto_data/gap_filling/safe_file_operations.py
gapless_crypto_data/gap_filling/universal_gap_filler.py
gapless_crypto_data/resume/__init__.py
gapless_crypto_data/resume/intelligent_checkpointing.py
gapless_crypto_data/sample_data/binance_spot_BTCUSDT-1d_20240101-20240102_v2.10.0.csv
gapless_crypto_data/sample_data/binance_spot_BTCUSDT-1d_20240101-20240102_v2.10.0.metadata.json
gapless_crypto_data/sample_data/binance_spot_BTCUSDT-1d_20240101-20240102_v2.5.0.csv
gapless_crypto_data/sample_data/binance_spot_BTCUSDT-1d_20240101-20240102_v2.5.0.metadata.json
gapless_crypto_data/sample_data/binance_spot_BTCUSDT-1d_20250819-20250831_v2.5.0.csv
gapless_crypto_data/sample_data/binance_spot_BTCUSDT-1d_20250819-20250831_v2.5.0.metadata.json
gapless_crypto_data/sample_data/binance_spot_BTCUSDT-1d_20250921-20250921_v2.10.0.csv
gapless_crypto_data/sample_data/binance_spot_BTCUSDT-1d_20250921-20250921_v2.10.0.metadata.json
gapless_crypto_data/sample_data/binance_spot_BTCUSDT-1d_20251002-20251002_v2.10.0.csv
gapless_crypto_data/sample_data/binance_spot_BTCUSDT-1d_20251002-20251002_v2.10.0.metadata.json
gapless_crypto_data/sample_data/binance_spot_BTCUSDT-1h_20240101-20240101_v2.5.0.csv
gapless_crypto_data/sample_data/binance_spot_BTCUSDT-1h_20240101-20240101_v2.5.0.metadata.json
gapless_crypto_data/sample_data/binance_spot_BTCUSDT-1h_20240101-20240102_v2.10.0.csv
gapless_crypto_data/sample_data/binance_spot_BTCUSDT-1h_20240101-20240102_v2.10.0.metadata.json
gapless_crypto_data-3.0.0.dist-info/METADATA
gapless_crypto_data-3.0.0.dist-info/WHEEL
gapless_crypto_data-3.0.0.dist-info/entry_points.txt
gapless_crypto_data-3.0.0.dist-info/licenses/AUTHORS.md
gapless_crypto_data-3.0.0.dist-info/licenses/LICENSE
gapless_crypto_data-3.0.0.dist-info/RECORD
