Metadata-Version: 2.4
Name: gapless-crypto-data
Version: 3.0.0
Summary: Ultra-fast cryptocurrency data collection with zero gaps guarantee. 22x faster via Binance public repository with complete 13-timeframe support (1s-1d) and intelligent monthly-to-daily fallback. Provides 11-column microstructure format with order flow metrics.
Project-URL: Homepage, https://github.com/Eon-Labs/gapless-crypto-data
Project-URL: Documentation, https://github.com/Eon-Labs/gapless-crypto-data#readme
Project-URL: Repository, https://github.com/Eon-Labs/gapless-crypto-data.git
Project-URL: Issues, https://github.com/Eon-Labs/gapless-crypto-data/issues
Project-URL: Changelog, https://github.com/Eon-Labs/gapless-crypto-data/blob/main/CHANGELOG.md
Author-email: Eon Labs <terry@eonlabs.com>
Maintainer-email: Terry Li <terry@eonlabs.com>
License: MIT
License-File: AUTHORS.md
License-File: LICENSE
Keywords: 13-timeframes,1s-1d,22x-faster,OHLCV,api,authentic-data,backward-compatibility,binance,ccxt,collection,crypto,cryptocurrency,data,download,dual-parameter,fetch-data,financial-data,function-based,gap-filling,gapless,interval,liquidity,microstructure,monthly-daily-fallback,order-flow,pandas,performance,taker-volume,time-series,timeframe,trading,ultra-high-frequency,zero-gaps
Classifier: Development Status :: 5 - Production/Stable
Classifier: Intended Audience :: Developers
Classifier: Intended Audience :: Financial and Insurance Industry
Classifier: License :: OSI Approved :: MIT License
Classifier: Operating System :: OS Independent
Classifier: Programming Language :: Python :: 3
Classifier: Programming Language :: Python :: 3.9
Classifier: Programming Language :: Python :: 3.10
Classifier: Programming Language :: Python :: 3.11
Classifier: Programming Language :: Python :: 3.12
Classifier: Programming Language :: Python :: 3.13
Classifier: Topic :: Office/Business :: Financial :: Investment
Classifier: Topic :: Scientific/Engineering :: Information Analysis
Classifier: Topic :: Software Development :: Libraries :: Python Modules
Requires-Python: >=3.9
Requires-Dist: httpx>=0.25.0
Requires-Dist: pandas>=2.0.0
Requires-Dist: pyarrow>=16.0.0
Provides-Extra: dev
Requires-Dist: black>=23.0.0; extra == 'dev'
Requires-Dist: mypy>=1.5.0; extra == 'dev'
Requires-Dist: pytest-cov>=4.0.0; extra == 'dev'
Requires-Dist: pytest>=7.0.0; extra == 'dev'
Requires-Dist: ruff>=0.1.0; extra == 'dev'
Provides-Extra: test
Requires-Dist: pytest-asyncio>=0.21.0; extra == 'test'
Requires-Dist: pytest-cov>=4.0.0; extra == 'test'
Requires-Dist: pytest>=7.0.0; extra == 'test'
